AioZohoAPI_SDP/__init__.py
AioZohoAPI_SDP/admin.py
AioZohoAPI_SDP/announcements.py
AioZohoAPI_SDP/approvals.py
AioZohoAPI_SDP/asset.py
AioZohoAPI_SDP/change.py
AioZohoAPI_SDP/cmdb.py
AioZohoAPI_SDP/comments.py
AioZohoAPI_SDP/contract.py
AioZohoAPI_SDP/device_registration.py
AioZohoAPI_SDP/personalization.py
AioZohoAPI_SDP/problem.py
AioZohoAPI_SDP/project.py
AioZohoAPI_SDP/purchase_order.py
AioZohoAPI_SDP/release.py
AioZohoAPI_SDP/report.py
AioZohoAPI_SDP/request.py
AioZohoAPI_SDP/sdp_aio_api_core.py
AioZohoAPI_SDP/solutions.py
AioZohoAPI_SDP/space.py
AioZohoAPI_SDP/task.py
AioZohoAPI_SDP/worklog.py
AioAPIZohoSDPlus-0.0.1.dist-info/METADATA
AioAPIZohoSDPlus-0.0.1.dist-info/WHEEL
AioAPIZohoSDPlus-0.0.1.dist-info/top_level.txt
AioAPIZohoSDPlus-0.0.1.dist-info/RECORD
