Metadata-Version: 2.1
Name: AioAPIZohoSDPlus
Version: 0.0.1
Summary: Этот модуль умеет работать с REST API Zoho SD Plus Manageengine через aiohttp
Home-page: https://github.com/azatkhafizov/aio_zoho_sdp_api
Author: AzatXafizov
Author-email: hafizov.azat.m@gmail.com
Project-URL: GitHub, https://github.com/azatkhafizov/aio_zoho_sdp_api
Keywords: Zoho zoho rest REST api API aiohttp
Classifier: Programming Language :: Python :: 3.11
Classifier: License :: OSI Approved :: MIT License
Classifier: Operating System :: OS Independent
Requires-Python: >=3.6
Requires-Dist: aiohttp ==3.9.1
